{
  "168032676651233": {
    "saldo": 182733,
    "reputasi": 12,
    "nama": "Bobi",
    "lastGacha": 1779872257846,
    "pasangan": "111416384184361",
    "lastKerja": 1779008357803,
    "kuotaKerja": {},
    "pekerjaan": "PNS",
    "lastGajian": 1779872225880
  },
  "21556944220222": {
    "saldo": 419763,
    "reputasi": 48,
    "lastKerja": 1779201784123,
    "nama": "Salomon",
    "lastGacha": 1779977763433,
    "pasangan": null,
    "pekerjaan": "PNS",
    "lastGajian": 1779978037732
  },
  "178392120950960": {
    "saldo": 146862,
    "reputasi": 24,
    "lastKerja": 1779720349892,
    "nama": "🐦‍🔥 pian",
    "lastGacha": 1779578948219,
    "pasangan": "256886758719623",
    "pekerjaan": "PNS",
    "lastGajian": 1779720833836,
    "kuotaKerja": {
      "sulit": {
        "jumlah": 1,
        "resetAt": 1779721249893
      }
    }
  },
  "229064145170580": {
    "saldo": 744325,
    "reputasi": 101,
    "lastKerja": 1779463646971,
    "nama": "🥵TEMBEMNITA🥵",
    "lastGacha": 1779977751560,
    "pekerjaan": "PNS",
    "lastGajian": 1779977477168,
    "pasangan": "75038078300307",
    "kuotaKerja": {
      "sulit": {
        "jumlah": 1,
        "resetAt": 1779464546972
      }
    },
    "mmr": 21
  },
  "256886758719623": {
    "saldo": 55922,
    "reputasi": 9,
    "lastKerja": 1779466581921,
    "nama": "Prince Rival",
    "lastGacha": 1779466526272,
    "pasangan": "178392120950960",
    "kuotaKerja": {
      "sulit": {
        "jumlah": 1,
        "resetAt": 1779467481921
      }
    }
  },
  "38517367435469": {
    "saldo": 10000,
    "reputasi": 0,
    "lastKerja": 1778835647479,
    "lastGacha": 1778770185033,
    "nama": "😜LIARNITA😜"
  },
  "29833430089855": {
    "saldo": 463262,
    "reputasi": 83,
    "lastKerja": 1780027971448,
    "nama": "🫦LEGITNITA🫦",
    "lastGacha": 1779979432791,
    "mmr": 52,
    "kuotaKerja": {
      "sulit": {
        "jumlah": 1,
        "resetAt": 1780028871451
      }
    },
    "pekerjaan": "PNS",
    "lastGajian": 1779979430087
  },
  "75038078300307": {
    "saldo": 647767,
    "reputasi": 35,
    "nama": "Z",
    "lastKerja": 1779431254612,
    "lastGacha": 1779951889870,
    "mmr": 0,
    "pekerjaan": "PNS",
    "lastGajian": 1780027759901,
    "pasangan": "229064145170580",
    "kuotaKerja": {}
  },
  "174921602854973": {
    "saldo": 15315,
    "reputasi": 27,
    "lastGacha": 1778770222170,
    "lastKerja": 1779160906439,
    "nama": "Dhinz"
  },
  "64592063512630": {
    "saldo": 202471,
    "reputasi": 24,
    "nama": "PTRA.S",
    "lastKerja": 1779873602954,
    "lastGacha": 1779981249853,
    "pekerjaan": "PNS",
    "lastGajian": 1779981244077,
    "kuotaKerja": {
      "sulit": {
        "jumlah": 2,
        "resetAt": 1779874385838
      }
    }
  },
  "185925007056938": {
    "saldo": 1408519,
    "reputasi": 98,
    "nama": "🌹MEKARLITA🌹",
    "lastKerja": 1779977877938,
    "lastGacha": 1779977702499,
    "mmr": 313,
    "pasangan": null,
    "pekerjaan": "PNS",
    "lastGajian": 1779977684067,
    "kuotaKerja": {
      "sulit": {
        "jumlah": 1,
        "resetAt": 1779978777938
      }
    }
  },
  "1435089526784": {
    "saldo": 18983,
    "reputasi": 5,
    "lastGacha": 1779872071295,
    "nama": "kumii❤️",
    "lastKerja": 1779192310030
  },
  "196993574010939": {
    "saldo": 11221,
    "reputasi": 15,
    "lastKerja": 1779662932799,
    "kuotaKerja": {
      "sulit": {
        "jumlah": 2,
        "resetAt": 1779663636048
      }
    },
    "lastGacha": 1779873350559,
    "nama": "mz kim"
  },
  "261224373690436": {
    "saldo": 2627,
    "reputasi": 60,
    "lastKerja": 1779891913574,
    "nama": "Reno Putra Mahkota",
    "kuotaKerja": {},
    "lastGacha": 1779582543038
  },
  "111416384184361": {
    "saldo": 26369,
    "reputasi": 15,
    "lastGacha": 1780025439884,
    "pasangan": "168032676651233",
    "nama": "Alwi 🤍 Bobi",
    "kuotaKerja": {
      "sulit": {
        "jumlah": 1,
        "resetAt": 1779890892729
      }
    },
    "lastKerja": 1779889992726
  },
  "137671385039053": {
    "saldo": 1234608,
    "reputasi": 44,
    "lastKerja": 1779333650197,
    "nama": "rey",
    "lastGacha": 1779454814278,
    "kuotaKerja": {
      "sulit": {
        "jumlah": 1,
        "resetAt": 1779334550197
      }
    },
    "pekerjaan": "PNS",
    "lastGajian": 1779448908307
  },
  "120363406553801682": {
    "saldo": 3820,
    "reputasi": 0,
    "lastKerja": 1778917401889
  },
  "107774335779006": {
    "saldo": 705904,
    "reputasi": 15,
    "nama": "😜LIARNITA😜",
    "lastKerja": 1779873235206,
    "lastGacha": 1779977757762,
    "mmr": 0,
    "pekerjaan": "PNS",
    "lastGajian": 1779977749123,
    "pasangan": null,
    "kuotaKerja": {
      "sulit": {
        "jumlah": 1,
        "resetAt": 1779874135207
      }
    }
  },
  "79482782257347": {
    "saldo": 7687,
    "reputasi": 10,
    "lastKerja": 1779206680739
  },
  "46446447456430": {
    "saldo": 10000,
    "reputasi": 0
  },
  "231250417713221": {
    "saldo": 190,
    "reputasi": 2,
    "lastKerja": 1778950219988,
    "nama": "Fajar",
    "pasangan": null,
    "mmr": 0
  },
  "149740545151215": {
    "saldo": 14221,
    "reputasi": 21,
    "lastKerja": 1779892644474,
    "nama": "KECOA",
    "kuotaKerja": {
      "sulit": {
        "jumlah": 3,
        "resetAt": 1779893092531
      }
    }
  },
  "209173564367025": {
    "saldo": 27181,
    "reputasi": 62,
    "lastKerja": 1779663018193,
    "nama": "barkah",
    "kuotaKerja": {
      "sulit": {
        "jumlah": 1,
        "resetAt": 1779663918194
      }
    },
    "lastGacha": 1779580548533,
    "mmr": 0
  },
  "230206639992897": {
    "saldo": 10000,
    "reputasi": 0
  },
  "173766357327942": {
    "saldo": 140,
    "reputasi": 3,
    "nama": "Bobi",
    "kuotaKerja": {
      "sulit": {
        "jumlah": 1,
        "resetAt": 1779438527514
      }
    },
    "lastKerja": 1779437627513,
    "lastGacha": 1779437644254
  },
  "259932058300477": {
    "saldo": 10000,
    "reputasi": 0
  },
  "179165332521048": {
    "saldo": 13016,
    "reputasi": 6,
    "lastKerja": 1779355113723,
    "kuotaKerja": {
      "sedang": {
        "jumlah": 2,
        "resetAt": 1779355759733
      }
    },
    "lastGacha": 1779578006776
  },
  "275101933113594": {
    "saldo": 10000,
    "reputasi": 0
  },
  "243396266487901": {
    "saldo": 10000,
    "reputasi": 0
  },
  "50273364009124": {
    "saldo": 95164,
    "reputasi": 29,
    "kuotaKerja": {
      "sulit": {
        "jumlah": 1,
        "resetAt": 1779978765329
      }
    },
    "lastKerja": 1779977865328,
    "nama": "PRINCESS LEBAH 🐝",
    "mmr": 0,
    "lastGacha": 1779977718177
  },
  "256362453987381": {
    "saldo": 0,
    "reputasi": 0
  },
  "72421822484621": {
    "saldo": 0,
    "reputasi": 0
  },
  "118829329944666": {
    "saldo": 0,
    "reputasi": 0
  },
  "2130605809801": {
    "saldo": 0,
    "reputasi": 0
  },
  "260975752175826": {
    "saldo": 0,
    "reputasi": 0
  },
  "16845197299742": {
    "saldo": 200,
    "reputasi": 0,
    "kuotaKerja": {},
    "lastKerja": 1779437308696
  },
  "68840490811393": {
    "saldo": 0,
    "reputasi": 0
  },
  "148219405307926": {
    "saldo": 0,
    "reputasi": 0
  },
  "240028710092831": {
    "saldo": 0,
    "reputasi": 0
  },
  "18460188930201": {
    "saldo": 0,
    "reputasi": 0
  },
  "52244301009009": {
    "saldo": 0,
    "reputasi": 0
  },
  "56367620612295": {
    "saldo": 0,
    "reputasi": 0
  },
  "20598713544931": {
    "saldo": 0,
    "reputasi": 0
  },
  "13078712287286": {
    "saldo": 0,
    "reputasi": 0
  },
  "158128549183717": {
    "saldo": 0,
    "reputasi": 0,
    "pasangan": null
  },
  "52377478508774": {
    "saldo": 0,
    "reputasi": 0,
    "kuotaKerja": {}
  },
  "80066797125639": {
    "saldo": 0,
    "reputasi": 0
  },
  "203543533359280": {
    "saldo": 1,
    "reputasi": 0
  },
  "230240831971567": {
    "saldo": 6087,
    "reputasi": 180,
    "nama": "DaffaCEO",
    "kuotaKerja": {
      "sulit": {
        "jumlah": 1,
        "resetAt": 1780027204183
      }
    },
    "lastKerja": 1780026304180,
    "lastGacha": 1779957765682
  }
}